sessionize/__init__.py
sessionize/exceptions.py
sessionize/orm/__init__.py
sessionize/orm/filter.py
sessionize/orm/iterators.py
sessionize/orm/selection.py
sessionize/orm/session_db.py
sessionize/orm/session_parent.py
sessionize/orm/session_table.py
sessionize/utils/__init__.py
sessionize/utils/alter.py
sessionize/utils/create.py
sessionize/utils/delete.py
sessionize/utils/drop.py
sessionize/utils/engine_integration.py
sessionize/utils/features.py
sessionize/utils/insert.py
sessionize/utils/select.py
sessionize/utils/session_integration.py
sessionize/utils/types.py
sessionize/utils/update.py
tests/__init__.py
tests/setup_test.py
tests/test_alter.py
tests/test_create.py
tests/test_delete.py
tests/test_drop.py
tests/test_engine_integration.py
tests/test_insert.py
tests/test_orm.py
tests/test_sa_orm.py
tests/test_select.py
tests/test_session_integration.py
tests/test_update.py
sessionize-0.0.18.dist-info/METADATA
sessionize-0.0.18.dist-info/WHEEL
sessionize-0.0.18.dist-info/top_level.txt
sessionize-0.0.18.dist-info/RECORD
