Metadata-Version: 2.1
Name: sessionize
Version: 0.0.18
Summary: Make changes to sql tables using SqlAlchmey sessions
Home-page: https://github.com/eddiethedean/sessionize
Author: Odos Matthews
Author-email: odosmatthews@gmail.com
License: MIT
Classifier: License :: OSI Approved :: MIT License
Classifier: Programming Language :: Python :: 3
Classifier: Programming Language :: Python :: 3.8
Classifier: Programming Language :: Python :: 3.9
Requires-Python: >=3.8
Requires-Dist: sqlalchemize
Requires-Dist: alembic (>=1.7.5)
Requires-Dist: chaingang
